lib/__init__.py
lib/api_20.py
adobe_analytics_api_20-0.0.1.dist-info/LICENSE.txt
adobe_analytics_api_20-0.0.1.dist-info/METADATA
adobe_analytics_api_20-0.0.1.dist-info/WHEEL
adobe_analytics_api_20-0.0.1.dist-info/top_level.txt
adobe_analytics_api_20-0.0.1.dist-info/RECORD
