Metadata-Version: 2.1
Name: adobe-analytics-api-20
Version: 0.0.1
Summary: Adobe Analytics API 2.0 Library
Home-page: https://github.com/framingeinstein/adobe-analytics-api
Author: Jason Morgan
Author-email: jason@framingeinstein.com
License: UNKNOWN
Platform: UNKNOWN
Classifier: Programming Language :: Python :: 3
Classifier: License :: OSI Approved :: MIT License
Classifier: Operating System :: OS Independent
Requires-Python: >=3.0
